git_fingerprint/__init__.py
git_fingerprint/__main__.py
git_fingerprint/exceptions.py
git_fingerprint/helpers.py
git_fingerprint/scanner.py
git_fingerprint-0.0.3.dist-info/METADATA
git_fingerprint-0.0.3.dist-info/RECORD
git_fingerprint-0.0.3.dist-info/WHEEL
git_fingerprint-0.0.3.dist-info/entry_points.txt
git_fingerprint-0.0.3.dist-info/top_level.txt
