Metadata-Version: 2.1
Name: git-fingerprint
Version: 0.0.3
Summary: Git Fingerprint is a web fingerprinting tool that attempts to scan a target based on the files a git repository by enumerating over all files ever found in the public web root and comparing cryptographic hashes of each commit, branch or tag in order to calculate the best possible match.
Home-page: https://github.com/Paradoxis/Git-Fingerprint
Author: Luke Paris (Paradoxis)
Author-email: luke@paradoxis.nl
License: MIT
Platform: UNKNOWN
Classifier: License :: OSI Approved :: MIT License
Classifier: Programming Language :: Python
Classifier: Programming Language :: Python :: 3
Classifier: Programming Language :: Python :: 3.6
Classifier: Programming Language :: Python :: Implementation :: CPython
Classifier: Programming Language :: Python :: Implementation :: PyPy
Requires-Python: >=3.6.0
Requires-Dist: GitPython (==2.1.8)
Requires-Dist: requests (==2.18.4)
Requires-Dist: tabulate (==0.8.2)
Requires-Dist: axel (==0.0.7)
Requires-Dist: progressbar2 (==3.34.3)
Requires-Dist: dicttoxml (==1.7.4)
